Operon-0.1.8.dist-info/METADATA
Operon-0.1.8.dist-info/RECORD
Operon-0.1.8.dist-info/WHEEL
Operon-0.1.8.dist-info/entry_points.txt
Operon-0.1.8.dist-info/top_level.txt
inquirer/__init__.py
inquirer/errors.py
inquirer/events.py
inquirer/prompt.py
inquirer/questions.py
inquirer/themes.py
inquirer/render/__init__.py
inquirer/render/console/__init__.py
inquirer/render/console/_checkbox.py
inquirer/render/console/_confirm.py
inquirer/render/console/_list.py
inquirer/render/console/_password.py
inquirer/render/console/_path.py
inquirer/render/console/_text.py
inquirer/render/console/base.py
operon/__init__.py
operon/components.py
operon/containers.py
operon/meta.py
operon/_cli/__init__.py
operon/_cli/_completer.py
operon/_cli/subcommands/__init__.py
operon/_cli/subcommands/batch_run.py
operon/_cli/subcommands/configure.py
operon/_cli/subcommands/help.py
operon/_cli/subcommands/init.py
operon/_cli/subcommands/install.py
operon/_cli/subcommands/list.py
operon/_cli/subcommands/run.py
operon/_cli/subcommands/settings.py
operon/_cli/subcommands/show.py
operon/_cli/subcommands/uninstall.py
operon/_util/__init__.py
operon/_util/apps.py
operon/_util/configs.py
operon/_util/errors.py
operon/_util/home.py
operon/_util/logging.py
operon/_util/settings.py
