Metadata-Version: 2.1
Name: Operon
Version: 0.1.8
Summary: Dataflow pipeline development framework, powered by Parsl
Home-page: https://github.com/djf604/operon
Author: Dominic Fitzgerald
Author-email: dominicfitzgerald11@gmail.com
License: GNU GPLv3
Download-URL: https://github.com/djf604/operon/tarball/0.1.8
Platform: UNKNOWN
Classifier: Development Status :: 4 - Beta
Classifier: Environment :: Console
Classifier: Intended Audience :: Developers
Classifier: Intended Audience :: Science/Research
Classifier: Programming Language :: Python
Classifier: Programming Language :: Python :: 3.5
Classifier: Programming Language :: Python :: 3.6
Classifier: Programming Language :: Python :: 3.7
Classifier: Programming Language :: Python :: 3 :: Only
Classifier: Topic :: Scientific/Engineering
Classifier: Topic :: Scientific/Engineering :: Bio-Informatics
Classifier: Topic :: Software Development :: Libraries
Classifier: License :: OSI Approved :: GNU General Public License v3 (GPLv3)
Requires-Dist: parsl (>=0.6.0)
Requires-Dist: ipyparallel
Requires-Dist: networkx (==2.0)
Requires-Dist: blessings (>=1.6)
Requires-Dist: readchar (==0.1.0)
Requires-Dist: tinydb (==3.9.0.post1)
